Metadata-Version: 2.1
Name: pytermcolor
Version: 0.0.1
Summary: Color formatting for output in terminal.
Home-page: https://gitlab.com/xcoponet/pytermcolor
Author: Xavier Coponet
Author-email: xavier.coponet@gmail.com
License: MIT
Platform: UNKNOWN
Classifier: Development Status :: 4 - Beta
Classifier: Environment :: Console
Classifier: Intended Audience :: Developers
Classifier: License :: OSI Approved :: MIT License
Classifier: Operating System :: OS Independent
Classifier: Programming Language :: Python
Classifier: Topic :: Terminals
